LICENSE
MANIFEST.in
README.md
setup.py
sige/__init__.py
sige/__version__.py
sige/common.cpp
sige/utils.py
sige.egg-info/PKG-INFO
sige.egg-info/SOURCES.txt
sige.egg-info/dependency_links.txt
sige.egg-info/requires.txt
sige.egg-info/top_level.txt
sige/cpu/common_cpu.cpp
sige/cpu/gather.cpp
sige/cpu/gather.h
sige/cpu/pybind_cpu.cpp
sige/cpu/scatter.cpp
sige/cpu/scatter.h
sige/cpu/scatter_gather.cpp
sige/cpu/scatter_gather.h
sige/cuda/common_cuda.cu
sige/cuda/gather.cpp
sige/cuda/gather_kernel.cu
sige/cuda/pybind_cuda.cpp
sige/cuda/scatter.cpp
sige/cuda/scatter_gather.cpp
sige/cuda/scatter_gather_kernel.cu
sige/cuda/scatter_kernel.cu
sige/mps/MPSDevice.h
sige/mps/MPSLibrary.h
sige/mps/MPSLibrary.mm
sige/mps/MPSStream.h
sige/mps/MPSUtils.h
sige/mps/common_mps.metal
sige/mps/gather.h
sige/mps/gather.metal
sige/mps/gather.mm
sige/mps/pybind_mps.cpp
sige/mps/scatter.h
sige/mps/scatter.metal
sige/mps/scatter.mm
sige/mps/scatter_gather.h
sige/mps/scatter_gather.metal
sige/mps/scatter_gather.mm
sige/nn/__init__.py
sige/nn/base.py
sige/nn/gather.py
sige/nn/scatter.py
sige/nn/scatter_gather.py
sige/nn/utils.py