Metadata-Version: 2.1
Name: sige
Version: 0.3.0
Summary: Spatially Incremental Generative Engine (SIGE)
Home-page: https://github.com/lmxyy/sige
Author: Muyang Li
Author-email: muyangli@cs.cmu.edu
Classifier: Programming Language :: Python :: 3
Classifier: Operating System :: OS Independent
License-File: LICENSE
